LICENSE
j_pandas_datalib/__init__.py
j_pandas_datalib/csv_tools.py
j_pandas_datalib/dataset.py
j_pandas_datalib/env_vars.py
j_pandas_datalib-0.1.1.dist-info/LICENSE
j_pandas_datalib-0.1.1.dist-info/METADATA
j_pandas_datalib-0.1.1.dist-info/WHEEL
j_pandas_datalib-0.1.1.dist-info/RECORD
