Metadata-Version: 2.1
Name: j-pandas-datalib
Version: 0.1.1
Summary: Dataabstractionlayer For Pandas
Home-page: https://github.com/OpenJKSoftware/j-pandas-datalib
License: LGPL-3
Keywords: pandas
Author: Joshua Kreuder
Author-email: joshua_kreuder@outlook.com
Requires-Python: >=3.8.1,<3.12
Classifier: License :: Other/Proprietary License
Classifier: Programming Language :: Python :: 3
Classifier: Programming Language :: Python :: 3.9
Classifier: Programming Language :: Python :: 3.10
Classifier: Programming Language :: Python :: 3.11
Requires-Dist: pandas (>=1.5.3,<2.0.0)
Requires-Dist: pytest-github-actions-annotate-failures (>=0.1.8,<0.2.0)
Project-URL: Repository, https://github.com/OpenJKSoftware/j-pandas-datalib
